data/__init__.py
data/read_word_files.py
logic/__init__.py
logic/param.py
logic/utils.py
logic/list_weak_model/__init__.py
logic/list_weak_model/list_based_model.py
presentation/__init__.py
weak_postagger/__init__.py
weak_postagger/data/__init__.py
weak_postagger/data/read_word_files.py
weak_postagger/logic/__init__.py
weak_postagger/logic/abbreviations.py
weak_postagger/logic/param.py
weak_postagger/logic/utils.py
weak_postagger/logic/label_disambiguation/__init__.py
weak_postagger/logic/label_disambiguation/rule_based_model.py
weak_postagger/logic/list_weak_model/__init__.py
weak_postagger/logic/list_weak_model/list_based_model.py
weak_postagger/logic/pipeline_builder/__init__.py
weak_postagger/logic/pipeline_builder/pipeline_weak_labeling.py
weak_postagger/presentation/__init__.py
weak_postagger/presentation/weak_labels.py
weak_postagger-0.1.2.dist-info/METADATA
weak_postagger-0.1.2.dist-info/WHEEL
weak_postagger-0.1.2.dist-info/top_level.txt
weak_postagger-0.1.2.dist-info/RECORD
