Metadata-Version: 2.1
Name: weak-postagger
Version: 0.1.2
Summary: Weak POS Tagging Model
Home-page: UNKNOWN
Author: Data & Analytics Research
Author-email: analytics.dar@take.net
Maintainer: daresearch
Maintainer-email: anaytics.dar@take.net
License: MIT License
Keywords: postagging,part of speech,weak modeling
Platform: UNKNOWN
Classifier: Programming Language :: Python :: 3
Classifier: Operating System :: OS Independent
Requires-Dist: pytest (==5.3.5)
Requires-Dist: Unidecode (==1.1.1)
Requires-Dist: take-text-preprocess (==0.0.5)
